{
  "version": 1,
  "last_updated": "2026-04-08",
  "purpose": "Priority ETF target universe for holdings extraction/refresh workflows.",
  "notes": [
    "This file is the actionable ETF holdings target list derived from the broader ETF context universe.",
    "trading-data should prioritize durable holdings coverage for this list before expanding wider.",
    "trading-model may still score/prune final usefulness downstream.",
    "Redundant broad-market duplicates (`VOO`, `IVV`, `VTI`) and redundant gold duplicate (`IAU`) were removed from the active holdings target list.",
    "Independent crypto proxy ETFs and relatively independent industry/thematic ETFs remain prioritized."
  ],
  "tiers": {
    "tier_1_core_broad_market": [
      "SPY",
      "QQQ",
      "IWM",
      "DIA"
    ],
    "tier_2_core_sector": [
      "XLK",
      "XLF",
      "XLE",
      "XLV",
      "XLI",
      "XLY",
      "XLP",
      "XLB",
      "XLU",
      "XLRE",
      "XLC"
    ],
    "tier_3_priority_macro_proxy": [
      "GLD",
      "SLV",
      "USO",
      "DBC",
      "PDBC",
      "IBIT",
      "ETHA"
    ],
    "tier_4_priority_industry_thematic": [
      "SMH",
      "SOXX",
      "KRE",
      "ITA",
      "IYT",
      "LIT",
      "GDX",
      "BOTZ"
    ]
  }
}
